__init__.py
gxd/algo_cli.py
gxd/cli.py
gxd/signer_cli.py
gxd-0.0.0a2.dist-info/licenses/LICENSE
gxd-0.0.0a2.dist-info/METADATA
gxd-0.0.0a2.dist-info/WHEEL
gxd-0.0.0a2.dist-info/entry_points.txt
gxd-0.0.0a2.dist-info/top_level.txt
gxd-0.0.0a2.dist-info/RECORD
