Metadata-Version: 2.4
Name: gxd
Version: 0.0.0a2
Summary: GXD – Block-based compression, algorithm analysis, and integrity tooling
Author-email: Muhammed Shafin p <not-required@example.com>
License: GPL-3.0
Project-URL: Homepage, https://github.com/hejhdiss/GXD
Project-URL: Source, https://github.com/hejhdiss/GXD
Requires-Python: >=3.8
License-File: LICENSE
Requires-Dist: tqdm; extra == "progress"
Provides-Extra: full
Requires-Dist: zstandard; extra == "full"
Requires-Dist: lz4; extra == "full"
Requires-Dist: brotli; extra == "full"
Requires-Dist: tqdm; extra == "full"
Dynamic: license-file
